pz_rail_projects-0.4.1.dist-info/licenses/LICENSE
rail/cli/rail_plot/__init__.py
rail/cli/rail_plot/__main__.py
rail/cli/rail_plot/plot_commands.py
rail/cli/rail_plot/plot_options.py
rail/cli/rail_project/__init__.py
rail/cli/rail_project/__main__.py
rail/cli/rail_project/project_commands.py
rail/cli/rail_project/project_options.py
rail/cli/rail_project/project_scripts.py
rail/plotting/__init__.py
rail/plotting/cat_data_holders.py
rail/plotting/cat_plotters.py
rail/plotting/control.py
rail/plotting/data_extraction_funcs.py
rail/plotting/dataset.py
rail/plotting/dataset_factory.py
rail/plotting/dataset_holder.py
rail/plotting/nz_data_holders.py
rail/plotting/nz_plotters.py
rail/plotting/plot_group.py
rail/plotting/plot_group_factory.py
rail/plotting/plot_holder.py
rail/plotting/plotter.py
rail/plotting/plotter_factory.py
rail/plotting/plotting_functions.py
rail/plotting/pz_data_holders.py
rail/plotting/pz_plotters.py
rail/plotting/utility_functions.py
rail/plotting/validation.py
rail/plotting/html_templates/bootstrap.min.css
rail/plotting/html_templates/plot_group_index.html
rail/plotting/html_templates/plot_group_table.html
rail/projects/__init__.py
rail/projects/_version.py
rail/projects/algorithm_factory.py
rail/projects/algorithm_holder.py
rail/projects/catalog_factory.py
rail/projects/catalog_template.py
rail/projects/configurable.py
rail/projects/dynamic_class.py
rail/projects/execution.py
rail/projects/factory_mixin.py
rail/projects/file_template.py
rail/projects/library.py
rail/projects/name_utils.py
rail/projects/path_funcs.py
rail/projects/pipeline_factory.py
rail/projects/pipeline_holder.py
rail/projects/project.py
rail/projects/project_file_factory.py
rail/projects/reducer.py
rail/projects/selection_factory.py
rail/projects/subsample_factory.py
rail/projects/subsampler.py
pz_rail_projects-0.4.1.dist-info/METADATA
pz_rail_projects-0.4.1.dist-info/WHEEL
pz_rail_projects-0.4.1.dist-info/entry_points.txt
pz_rail_projects-0.4.1.dist-info/top_level.txt
pz_rail_projects-0.4.1.dist-info/RECORD
