Metadata-Version: 2.4
Name: pz-rail-projects
Version: 0.4.1
Summary: RAIL Project files
Author-email: The LSST DESC PZ WG <echarles@slac.stanford.edu>
License: MIT License
Classifier: Development Status :: 4 - Beta
Classifier: License :: OSI Approved :: MIT License
Classifier: Intended Audience :: Developers
Classifier: Intended Audience :: Science/Research
Classifier: Programming Language :: Python
Classifier: Programming Language :: Python :: 3
Classifier: Programming Language :: Python :: 3.10
Classifier: Natural Language :: English
Classifier: Operating System :: POSIX
Requires-Python: >=3.10
License-File: LICENSE
Requires-Dist: pz-rail-pipelines
Requires-Dist: pz-rail-sompz
Requires-Dist: pz-rail-calib
Requires-Dist: matplotlib
Requires-Dist: yamllint
Requires-Dist: pyarrow
Requires-Dist: jinja2
Requires-Dist: tables_io[full]
Provides-Extra: full
Requires-Dist: pz-rail-pipelines[full]; extra == "full"
Provides-Extra: dev
Requires-Dist: pz-rail-pipelines[full]; extra == "dev"
Requires-Dist: coverage; extra == "dev"
Requires-Dist: pytest; extra == "dev"
Requires-Dist: pytest-cov; extra == "dev"
Requires-Dist: pre-commit; extra == "dev"
Requires-Dist: pylint; extra == "dev"
Provides-Extra: docs
Requires-Dist: nbsphinx; extra == "docs"
Requires-Dist: sphinx; extra == "docs"
Requires-Dist: sphinx-autodoc-typehints; extra == "docs"
Requires-Dist: sphinx_rtd_theme; extra == "docs"
Requires-Dist: sphinx-autoapi; extra == "docs"
Requires-Dist: sphinx-tabs; extra == "docs"
Requires-Dist: sphinx-click; extra == "docs"
Dynamic: license-file
